XStatic_Chosen-0.13.0.1-py3.13-nspkg.pth
xstatic/pkg/chosen/__init__.py
xstatic/pkg/chosen/data/chosen-sprite.png
xstatic/pkg/chosen/data/chosen-sprite@2x.png
xstatic/pkg/chosen/data/chosen.css
xstatic/pkg/chosen/data/chosen.jquery.js
xstatic/pkg/chosen/data/chosen.jquery.min.js
xstatic/pkg/chosen/data/chosen.min.css
xstatic/pkg/chosen/data/chosen.proto.js
xstatic/pkg/chosen/data/chosen.proto.min.js
xstatic/pkg/chosen/data/index.html
xstatic/pkg/chosen/data/index.proto.html
xstatic/pkg/chosen/data/index.width.html
xstatic/pkg/chosen/data/docsupport/chosen.png
xstatic/pkg/chosen/data/docsupport/oss-credit.png
xstatic/pkg/chosen/data/docsupport/style.css
xstatic_chosen-0.13.0.1.dist-info/METADATA
xstatic_chosen-0.13.0.1.dist-info/WHEEL
xstatic_chosen-0.13.0.1.dist-info/namespace_packages.txt
xstatic_chosen-0.13.0.1.dist-info/top_level.txt
xstatic_chosen-0.13.0.1.dist-info/RECORD
