Metadata-Version: 2.4
Name: XStatic-Chosen
Version: 0.13.0.1
Summary: Chosen 0.13.0 (XStatic packaging standard)
Home-page: http://harvesthq.github.io/chosen/
Maintainer: Cheer Xiao
Maintainer-email: xiaqqaix@gmail.com
License: (same as Chosen)
Keywords: chosen xstatic
Platform: any
Dynamic: description
Dynamic: home-page
Dynamic: keywords
Dynamic: license
Dynamic: maintainer
Dynamic: maintainer-email
Dynamic: platform
Dynamic: summary
